veilid/__init__.py
veilid/api.py
veilid/config.py
veilid/connection.py
veilid/error.py
veilid/json_api.py
veilid/operations.py
veilid/state.py
veilid/types.py
veilid/schema/RecvMessage.json
veilid/schema/Request.json
veilid-0.5.0.dist-info/METADATA
veilid-0.5.0.dist-info/WHEEL
veilid-0.5.0.dist-info/licenses/LICENSE.md
veilid-0.5.0.dist-info/RECORD
