Metadata-Version: 2.4
Name: veilid
Version: 0.5.0
Summary: Create an application in Python using the distributed Veilid framework for private, E2EE, app-to-app communication.
Project-URL: homepage, https://veilid.com
Project-URL: repository, https://gitlab.com/veilid/veilid
Author-email: Veilid Team <contact@veilid.com>
License-Expression: MPL-2.0
License-File: LICENSE.md
Requires-Python: <4,>=3.12.5
Requires-Dist: appdirs<2,>=1.4.4
Requires-Dist: jsonschema<5,>=4.17.3
